{
	"format_version": "1.21.6",
	"credit": "Made with Blockbench",
	"texture_size": [32, 32],
	"textures": {
		"1": "epicfight:item/diamond_tachi",
		"particle": "epicfight:item/diamond_tachi"
	},
	"elements": [
		{
			"from": [7.2, -10.3, 6.4],
			"to": [8, -0.9, 7.8],
			"rotation": {"angle": 0, "axis": "y", "origin": [7, -9.1, 6]},
			"faces": {
				"north": {"uv": [3.5, 0, 4, 4.75], "texture": "#1"},
				"east": {"uv": [1.25, 0, 0.5, 4.75], "texture": "#1"},
				"south": {"uv": [4, 0, 4.5, 4.75], "texture": "#1"},
				"west": {"uv": [0.5, 0, 1.25, 4.75], "texture": "#1"},
				"up": {"uv": [5, 0.75, 4.5, 0], "texture": "#1"},
				"down": {"uv": [5, 1, 4.5, 1.75], "texture": "#1"}
			}
		},
		{
			"from": [8.2, -1, 5.7],
			"to": [8.6, -0.3, 8.6],
			"rotation": {"angle": 0, "axis": "y", "origin": [6.1, -1, 5.8]},
			"faces": {
				"north": {"uv": [8.5, 7.5, 8.75, 7.75], "texture": "#1"},
				"east": {"uv": [4.5, 2, 6, 2.25], "texture": "#1"},
				"south": {"uv": [8, 8.5, 8.25, 8.75], "texture": "#1"},
				"west": {"uv": [4.5, 2.5, 6, 2.75], "texture": "#1"},
				"up": {"uv": [4.75, 4.5, 4.5, 3], "texture": "#1"},
				"down": {"uv": [4.75, 4.5, 4.5, 6], "texture": "#1"}
			}
		},
		{
			"from": [6.6, -1, 5.7],
			"to": [7, -0.3, 8.6],
			"rotation": {"angle": 0, "axis": "y", "origin": [4.5, -1, 5.8]},
			"faces": {
				"north": {"uv": [10.5, 2, 10.75, 2.25], "texture": "#1"},
				"east": {"uv": [5, 0, 6.5, 0.25], "texture": "#1"},
				"south": {"uv": [10.5, 2.5, 10.75, 2.75], "texture": "#1"},
				"west": {"uv": [5, 0.5, 6.5, 0.75], "texture": "#1"},
				"up": {"uv": [0.75, 6.5, 0.5, 5], "texture": "#1"},
				"down": {"uv": [1.25, 5, 1, 6.5], "texture": "#1"}
			}
		},
		{
			"from": [7.3, -0.4, 6.2],
			"to": [7.9, 0.2, 8.1],
			"rotation": {"angle": 0, "axis": "y", "origin": [7, 1, 6.1]},
			"faces": {
				"north": {"uv": [8.5, 8, 8.75, 8.25], "texture": "#1"},
				"east": {"uv": [5, 5, 6, 5.25], "texture": "#1"},
				"south": {"uv": [8.5, 8.5, 8.75, 8.75], "texture": "#1"},
				"west": {"uv": [5.5, 1, 6.5, 1.25], "texture": "#1"},
				"up": {"uv": [5.75, 4, 5.5, 3], "texture": "#1"},
				"down": {"uv": [5.25, 5.5, 5, 6.5], "texture": "#1"}
			}
		},
		{
			"from": [7.3, 0.19497, 6.66997],
			"to": [7.9, 0.66997, 7.62997],
			"rotation": {"angle": 0, "axis": "y", "origin": [7, 0.99497, 6.09497]},
			"faces": {
				"north": {"uv": [9.5, 5.5, 9.75, 5.75], "texture": "#1"},
				"east": {"uv": [8, 0, 8.5, 0.25], "texture": "#1"},
				"south": {"uv": [6, 9.5, 6.25, 9.75], "texture": "#1"},
				"west": {"uv": [0.5, 8, 1, 8.25], "texture": "#1"},
				"up": {"uv": [8.25, 1, 8, 0.5], "texture": "#1"},
				"down": {"uv": [1.25, 8, 1, 8.5], "texture": "#1"}
			}
		},
		{
			"from": [7.305, -0.87355, 7.40777],
			"to": [7.895, -0.48355, 8.07277],
			"rotation": {"angle": 45, "axis": "x", "origin": [7, -0.17855, 8.90277]},
			"faces": {
				"north": {"uv": [9, 0, 9.25, 0.25], "texture": "#1"},
				"east": {"uv": [0.5, 9, 0.75, 9.25], "texture": "#1"},
				"south": {"uv": [9, 0.5, 9.25, 0.75], "texture": "#1"},
				"west": {"uv": [1, 9, 1.25, 9.25], "texture": "#1"},
				"up": {"uv": [9.25, 1.25, 9, 1], "texture": "#1"},
				"down": {"uv": [9.25, 1.5, 9, 1.75], "texture": "#1"}
			}
		},
		{
			"from": [7.305, 0.02173, 7.22246],
			"to": [7.895, 0.68673, 7.61246],
			"rotation": {"angle": 45, "axis": "x", "origin": [7, 1.34173, 6.91746]},
			"faces": {
				"north": {"uv": [9.5, 4, 9.75, 4.25], "texture": "#1"},
				"east": {"uv": [4.5, 9.5, 4.75, 9.75], "texture": "#1"},
				"south": {"uv": [9.5, 4.5, 9.75, 4.75], "texture": "#1"},
				"west": {"uv": [5, 9.5, 5.25, 9.75], "texture": "#1"},
				"up": {"uv": [9.75, 5.25, 9.5, 5], "texture": "#1"},
				"down": {"uv": [5.75, 9.5, 5.5, 9.75], "texture": "#1"}
			}
		},
		{
			"from": [7.4, -1.1, 7],
			"to": [7.8, 24.6, 7.9],
			"rotation": {"angle": 0, "axis": "y", "origin": [7, 1, 6.1]},
			"faces": {
				"north": {"uv": [1.5, 0, 1.75, 12.75], "texture": "#1"},
				"east": {"uv": [0, 0, 0.5, 12.75], "texture": "#1"},
				"south": {"uv": [2, 0, 2.25, 12.75], "texture": "#1"},
				"west": {"uv": [0.5, 0, 0, 12.75], "texture": "#1"},
				"up": {"uv": [4.75, 7.5, 4.5, 7], "texture": "#1"},
				"down": {"uv": [7.25, 4.5, 7, 5], "texture": "#1"}
			}
		},
		{
			"from": [7.5, -1.1, 6.3],
			"to": [7.7, 24.6, 6.8],
			"rotation": {"angle": 0, "axis": "y", "origin": [7, 1, 6.1]},
			"faces": {
				"north": {"uv": [2.5, 0, 2.75, 12.75], "texture": "#1"},
				"east": {"uv": [3, 0, 3.25, 12.75], "texture": "#1"},
				"south": {"uv": [2.75, 0, 2.5, 12.75], "texture": "#1"},
				"west": {"uv": [3, 0, 3.25, 12.75], "texture": "#1"},
				"up": {"uv": [9.25, 2.25, 9, 2], "texture": "#1"},
				"down": {"uv": [9.25, 2.5, 9, 2.75], "texture": "#1"}
			}
		},
		{
			"from": [7.3, -9.12777, 5.81182],
			"to": [7.9, -8.12777, 6.21182],
			"rotation": {"angle": 22.5, "axis": "x", "origin": [5.8, -8.72777, 5.41182]},
			"faces": {
				"north": {"uv": [7, 5, 7.25, 5.5], "texture": "#1"},
				"east": {"uv": [7, 5.5, 7.25, 6], "texture": "#1"},
				"south": {"uv": [7, 6, 7.25, 6.5], "texture": "#1"},
				"west": {"uv": [6.5, 7, 6.75, 7.5], "texture": "#1"},
				"up": {"uv": [9.25, 3.25, 9, 3], "texture": "#1"},
				"down": {"uv": [3.75, 9, 3.5, 9.25], "texture": "#1"}
			}
		},
		{
			"from": [7.3, -9.18867, 7.70067],
			"to": [7.9, -8.18867, 8.10067],
			"rotation": {"angle": -22.5, "axis": "x", "origin": [5.8, -7.98867, 8.50067]},
			"faces": {
				"north": {"uv": [7, 7, 7.25, 7.5], "texture": "#1"},
				"east": {"uv": [0.5, 7.5, 0.75, 8], "texture": "#1"},
				"south": {"uv": [7.5, 0.5, 7.75, 1], "texture": "#1"},
				"west": {"uv": [1, 7.5, 1.25, 8], "texture": "#1"},
				"up": {"uv": [9.25, 3.75, 9, 3.5], "texture": "#1"},
				"down": {"uv": [4.25, 9, 4, 9.25], "texture": "#1"}
			}
		},
		{
			"from": [7.3, -9.77052, 7.17554],
			"to": [7.9, -9.37052, 7.97554],
			"rotation": {"angle": -22.5, "axis": "x", "origin": [5.8, -8.97052, 7.17554]},
			"faces": {
				"north": {"uv": [10.5, 3.5, 10.75, 3.75], "texture": "#1"},
				"east": {"uv": [8, 7, 8.5, 7.25], "texture": "#1"},
				"south": {"uv": [4, 10.5, 4.25, 10.75], "texture": "#1"},
				"west": {"uv": [7.5, 8, 8, 8.25], "texture": "#1"},
				"up": {"uv": [8.25, 8, 8, 7.5], "texture": "#1"},
				"down": {"uv": [8.25, 8, 8, 8.5], "texture": "#1"}
			}
		},
		{
			"from": [7.3, -9.67916, 5.78388],
			"to": [7.9, -9.27916, 6.58388],
			"rotation": {"angle": 22.5, "axis": "x", "origin": [5.8, -10.07916, 6.58388]},
			"faces": {
				"north": {"uv": [10.5, 4, 10.75, 4.25], "texture": "#1"},
				"east": {"uv": [8.5, 0, 9, 0.25], "texture": "#1"},
				"south": {"uv": [4.5, 10.5, 4.75, 10.75], "texture": "#1"},
				"west": {"uv": [0.5, 8.5, 1, 8.75], "texture": "#1"},
				"up": {"uv": [8.75, 1, 8.5, 0.5], "texture": "#1"},
				"down": {"uv": [1.25, 8.5, 1, 9], "texture": "#1"}
			}
		},
		{
			"from": [7.29, -8.61, 5.89],
			"to": [7.91, -8.19, 8.31],
			"rotation": {"angle": 0, "axis": "y", "origin": [6.1, -9, 5.8]},
			"faces": {
				"north": {"uv": [9, 4, 9.25, 4.25], "texture": "#1"},
				"east": {"uv": [5, 4, 6.25, 4.25], "texture": "#1"},
				"south": {"uv": [4.5, 9, 4.75, 9.25], "texture": "#1"},
				"west": {"uv": [5, 4.5, 6.25, 4.75], "texture": "#1"},
				"up": {"uv": [3.75, 6.25, 3.5, 5], "texture": "#1"},
				"down": {"uv": [4.25, 5, 4, 6.25], "texture": "#1"}
			}
		},
		{
			"from": [7.1, -9.70961, 6.31195],
			"to": [8.1, -9.30961, 7.91195],
			"rotation": {"angle": 0, "axis": "y", "origin": [6.1, -10.10961, 5.81195]},
			"faces": {
				"north": {"uv": [8.5, 1, 9, 1.25], "texture": "#1"},
				"east": {"uv": [6.5, 6.5, 7.25, 6.75], "texture": "#1"},
				"south": {"uv": [8.5, 1.5, 9, 1.75], "texture": "#1"},
				"west": {"uv": [7, 0, 7.75, 0.25], "texture": "#1"},
				"up": {"uv": [5.5, 1.75, 5, 1], "texture": "#1"},
				"down": {"uv": [5.5, 3, 5, 3.75], "texture": "#1"}
			}
		},
		{
			"from": [7.4, 26.48966, -0.69996],
			"to": [7.8, 27.68966, -0.22496],
			"rotation": {"angle": 22.5, "axis": "x", "origin": [7, 6.18966, -1.59996]},
			"faces": {
				"north": {"uv": [7.5, 3, 7.75, 3.5], "texture": "#1"},
				"east": {"uv": [3.5, 7.5, 3.75, 8], "texture": "#1"},
				"south": {"uv": [4, 7.5, 4.25, 8], "texture": "#1"},
				"west": {"uv": [4.5, 7.5, 4.75, 8], "texture": "#1"},
				"up": {"uv": [9.25, 4.75, 9, 4.5], "texture": "#1"},
				"down": {"uv": [5.25, 9, 5, 9.25], "texture": "#1"}
			}
		},
		{
			"from": [7.1, -8.35187, 5.79722],
			"to": [8.1, -7.85187, 6.49722],
			"rotation": {"angle": -22.5, "axis": "x", "origin": [7, -7.55187, 7.09722]},
			"faces": {
				"north": {"uv": [7.5, 4.5, 8, 4.75], "texture": "#1"},
				"east": {"uv": [9, 5, 9.25, 5.25], "texture": "#1"},
				"south": {"uv": [5, 7.5, 5.5, 7.75], "texture": "#1"},
				"west": {"uv": [5.5, 9, 5.75, 9.25], "texture": "#1"},
				"up": {"uv": [8, 5.25, 7.5, 5], "texture": "#1"},
				"down": {"uv": [6, 7.5, 5.5, 7.75], "texture": "#1"}
			}
		},
		{
			"from": [7.1, -8.26813, 7.30046],
			"to": [8.1, -7.76813, 8.00046],
			"rotation": {"angle": 22.5, "axis": "x", "origin": [7, -8.56813, 6.70046]},
			"faces": {
				"north": {"uv": [8, 6, 8.5, 6.25], "texture": "#1"},
				"east": {"uv": [10.5, 3, 10.75, 3.25], "texture": "#1"},
				"south": {"uv": [6.5, 8, 7, 8.25], "texture": "#1"},
				"west": {"uv": [3.5, 10.5, 3.75, 10.75], "texture": "#1"},
				"up": {"uv": [8.5, 6.75, 8, 6.5], "texture": "#1"},
				"down": {"uv": [7.5, 8, 7, 8.25], "texture": "#1"}
			}
		},
		{
			"from": [7.4, 24.6, 7.7],
			"to": [7.8, 26.4, 7.9],
			"rotation": {"angle": 0, "axis": "y", "origin": [7, 1, 6.1]},
			"faces": {
				"north": {"uv": [5.5, 5.5, 5.75, 6.5], "texture": "#1"},
				"east": {"uv": [6, 1.5, 6.25, 2.5], "texture": "#1"},
				"south": {"uv": [6, 2.5, 6.25, 3.5], "texture": "#1"},
				"west": {"uv": [4.5, 6, 4.75, 7], "texture": "#1"},
				"up": {"uv": [9.25, 5.75, 9, 5.5], "texture": "#1"},
				"down": {"uv": [6.25, 9, 6, 9.25], "texture": "#1"}
			}
		},
		{
			"from": [7.4, 25.98586, 8.73201],
			"to": [7.8, 26.23586, 9.08201],
			"rotation": {"angle": -45, "axis": "x", "origin": [5.8, 24.43586, 8.73201]},
			"faces": {
				"north": {"uv": [9, 6, 9.25, 6.25], "texture": "#1"},
				"east": {"uv": [6.5, 9, 6.75, 9.25], "texture": "#1"},
				"south": {"uv": [9, 6.5, 9.25, 6.75], "texture": "#1"},
				"west": {"uv": [7, 9, 7.25, 9.25], "texture": "#1"},
				"up": {"uv": [9.25, 7.25, 9, 7], "texture": "#1"},
				"down": {"uv": [7.75, 9, 7.5, 9.25], "texture": "#1"}
			}
		},
		{
			"from": [7.5, 26.23721, -1.33083],
			"to": [7.7, 27.73721, -0.83083],
			"rotation": {"angle": 22.5, "axis": "x", "origin": [7, 6.23721, -1.63083]},
			"faces": {
				"north": {"uv": [5, 6.5, 5.25, 7.25], "texture": "#1"},
				"east": {"uv": [5.5, 6.5, 5.75, 7.25], "texture": "#1"},
				"south": {"uv": [6.5, 5.5, 6.75, 6.25], "texture": "#1"},
				"west": {"uv": [6, 6.5, 6.25, 7.25], "texture": "#1"},
				"up": {"uv": [9.25, 7.75, 9, 7.5], "texture": "#1"},
				"down": {"uv": [8.25, 9, 8, 9.25], "texture": "#1"}
			}
		},
		{
			"from": [7.5, 26.27161, 8.28824],
			"to": [7.7, 26.57161, 9.43824],
			"rotation": {"angle": -45, "axis": "x", "origin": [5.7, 24.57161, 8.28824]},
			"faces": {
				"north": {"uv": [9, 8, 9.25, 8.25], "texture": "#1"},
				"east": {"uv": [7.5, 5.5, 8, 5.75], "texture": "#1"},
				"south": {"uv": [8.5, 9, 8.75, 9.25], "texture": "#1"},
				"west": {"uv": [6, 7.5, 6.5, 7.75], "texture": "#1"},
				"up": {"uv": [7.75, 6.5, 7.5, 6], "texture": "#1"},
				"down": {"uv": [6.75, 7.5, 6.5, 8], "texture": "#1"}
			}
		},
		{
			"from": [7.5, 26.09364, 7.65184],
			"to": [7.7, 26.58864, 7.90184],
			"rotation": {"angle": 0, "axis": "y", "origin": [7, 24.99364, 6.05184]},
			"faces": {
				"north": {"uv": [9, 8.5, 9.25, 8.75], "texture": "#1"},
				"east": {"uv": [9, 9, 9.25, 9.25], "texture": "#1"},
				"south": {"uv": [9.5, 0, 9.75, 0.25], "texture": "#1"},
				"west": {"uv": [0.5, 9.5, 0.75, 9.75], "texture": "#1"},
				"up": {"uv": [9.75, 0.75, 9.5, 0.5], "texture": "#1"},
				"down": {"uv": [1.25, 9.5, 1, 9.75], "texture": "#1"}
			}
		},
		{
			"from": [7.5, 26.07161, 8.28824],
			"to": [7.7, 26.29661, 9.08824],
			"rotation": {"angle": -45, "axis": "x", "origin": [5.7, 24.57161, 8.28824]},
			"faces": {
				"north": {"uv": [9.5, 1, 9.75, 1.25], "texture": "#1"},
				"east": {"uv": [7.5, 6.5, 8, 6.75], "texture": "#1"},
				"south": {"uv": [9.5, 1.5, 9.75, 1.75], "texture": "#1"},
				"west": {"uv": [7, 7.5, 7.5, 7.75], "texture": "#1"},
				"up": {"uv": [7.75, 7.5, 7.5, 7], "texture": "#1"},
				"down": {"uv": [7.75, 7.5, 7.5, 8], "texture": "#1"}
			}
		},
		{
			"from": [7.41, 26.61551, -0.36692],
			"to": [7.79, 27.17051, -0.03692],
			"rotation": {"angle": 22.5, "axis": "x", "origin": [7, 6.20551, -1.57692]},
			"faces": {
				"north": {"uv": [9.5, 2, 9.75, 2.25], "texture": "#1"},
				"east": {"uv": [9.5, 2.5, 9.75, 2.75], "texture": "#1"},
				"south": {"uv": [9.5, 3, 9.75, 3.25], "texture": "#1"},
				"west": {"uv": [3.5, 9.5, 3.75, 9.75], "texture": "#1"},
				"up": {"uv": [9.75, 3.75, 9.5, 3.5], "texture": "#1"},
				"down": {"uv": [4.25, 9.5, 4, 9.75], "texture": "#1"}
			}
		},
		{
			"from": [7.3, 2.4, 7.1],
			"to": [7.9, 2.7, 7.4],
			"rotation": {"angle": 0, "axis": "y", "origin": [5.9, 0, 5.5]},
			"faces": {
				"north": {"uv": [9.5, 6, 9.75, 6.25], "texture": "#1"},
				"east": {"uv": [6.5, 9.5, 6.75, 9.75], "texture": "#1"},
				"south": {"uv": [9.5, 6.5, 9.75, 6.75], "texture": "#1"},
				"west": {"uv": [7, 9.5, 7.25, 9.75], "texture": "#1"},
				"up": {"uv": [9.75, 7.25, 9.5, 7], "texture": "#1"},
				"down": {"uv": [7.75, 9.5, 7.5, 9.75], "texture": "#1"}
			}
		},
		{
			"from": [7, -9.2, 9.275],
			"to": [8.2, -8.3, 10.175],
			"rotation": {"angle": -45, "axis": "x", "origin": [5.9, -11.6, 7.675]},
			"faces": {
				"north": {"uv": [5.5, 1.5, 6, 2], "texture": "#1"},
				"east": {"uv": [6, 3.5, 6.5, 4], "texture": "#1"},
				"south": {"uv": [6, 5, 6.5, 5.5], "texture": "#1"},
				"west": {"uv": [6, 5.5, 6.5, 6], "texture": "#1"},
				"up": {"uv": [6.5, 6.5, 6, 6], "texture": "#1"},
				"down": {"uv": [7, 0, 6.5, 0.5], "texture": "#1"}
			}
		},
		{
			"from": [7.3, 4.71421, 7.58579],
			"to": [7.9, 5.51421, 7.88579],
			"rotation": {"angle": 45, "axis": "x", "origin": [5.9, 4.71421, 6.08579]},
			"faces": {
				"north": {"uv": [8, 3, 8.25, 3.5], "texture": "#1"},
				"east": {"uv": [3.5, 8, 3.75, 8.5], "texture": "#1"},
				"south": {"uv": [8, 3.5, 8.25, 4], "texture": "#1"},
				"west": {"uv": [4, 8, 4.25, 8.5], "texture": "#1"},
				"up": {"uv": [10.25, 4.25, 10, 4], "texture": "#1"},
				"down": {"uv": [4.75, 10, 4.5, 10.25], "texture": "#1"}
			}
		},
		{
			"from": [7.3, 3.91924, 7.71213],
			"to": [7.9, 4.21924, 8.01213],
			"rotation": {"angle": 0, "axis": "y", "origin": [5.9, 1.51924, 6.41213]},
			"faces": {
				"north": {"uv": [10, 2, 10.25, 2.25], "texture": "#1"},
				"east": {"uv": [10, 2.5, 10.25, 2.75], "texture": "#1"},
				"south": {"uv": [10, 3, 10.25, 3.25], "texture": "#1"},
				"west": {"uv": [3.5, 10, 3.75, 10.25], "texture": "#1"},
				"up": {"uv": [10.25, 3.75, 10, 3.5], "texture": "#1"},
				"down": {"uv": [4.25, 10, 4, 10.25], "texture": "#1"}
			}
		},
		{
			"from": [7.3, 3.4, 7.1],
			"to": [7.9, 3.7, 7.4],
			"rotation": {"angle": 0, "axis": "y", "origin": [5.9, 1, 5.5]},
			"faces": {
				"north": {"uv": [10, 0, 10.25, 0.25], "texture": "#1"},
				"east": {"uv": [0.5, 10, 0.75, 10.25], "texture": "#1"},
				"south": {"uv": [10, 0.5, 10.25, 0.75], "texture": "#1"},
				"west": {"uv": [1, 10, 1.25, 10.25], "texture": "#1"},
				"up": {"uv": [10.25, 1.25, 10, 1], "texture": "#1"},
				"down": {"uv": [10.25, 1.5, 10, 1.75], "texture": "#1"}
			}
		},
		{
			"from": [7.3, 5.91924, 7.71213],
			"to": [7.9, 6.21924, 8.01213],
			"rotation": {"angle": 0, "axis": "y", "origin": [5.9, 3.51924, 6.41213]},
			"faces": {
				"north": {"uv": [10.5, 0, 10.75, 0.25], "texture": "#1"},
				"east": {"uv": [0.5, 10.5, 0.75, 10.75], "texture": "#1"},
				"south": {"uv": [10.5, 0.5, 10.75, 0.75], "texture": "#1"},
				"west": {"uv": [1, 10.5, 1.25, 10.75], "texture": "#1"},
				"up": {"uv": [10.75, 1.25, 10.5, 1], "texture": "#1"},
				"down": {"uv": [10.75, 1.5, 10.5, 1.75], "texture": "#1"}
			}
		},
		{
			"from": [7.3, 6.71421, 7.58579],
			"to": [7.9, 7.51421, 7.88579],
			"rotation": {"angle": 45, "axis": "x", "origin": [5.9, 6.71421, 6.08579]},
			"faces": {
				"north": {"uv": [8, 5, 8.25, 5.5], "texture": "#1"},
				"east": {"uv": [5.5, 8, 5.75, 8.5], "texture": "#1"},
				"south": {"uv": [8, 5.5, 8.25, 6], "texture": "#1"},
				"west": {"uv": [6, 8, 6.25, 8.5], "texture": "#1"},
				"up": {"uv": [10.25, 9.75, 10, 9.5], "texture": "#1"},
				"down": {"uv": [10.25, 10, 10, 10.25], "texture": "#1"}
			}
		},
		{
			"from": [7.3, 5.4, 7.1],
			"to": [7.9, 5.7, 7.4],
			"rotation": {"angle": 0, "axis": "y", "origin": [5.9, 3, 5.5]},
			"faces": {
				"north": {"uv": [10, 8, 10.25, 8.25], "texture": "#1"},
				"east": {"uv": [8.5, 10, 8.75, 10.25], "texture": "#1"},
				"south": {"uv": [10, 8.5, 10.25, 8.75], "texture": "#1"},
				"west": {"uv": [9, 10, 9.25, 10.25], "texture": "#1"},
				"up": {"uv": [10.25, 9.25, 10, 9], "texture": "#1"},
				"down": {"uv": [9.75, 10, 9.5, 10.25], "texture": "#1"}
			}
		},
		{
			"from": [7.3, 5.71421, 7.58579],
			"to": [7.9, 6.51421, 7.88579],
			"rotation": {"angle": 45, "axis": "x", "origin": [5.9, 5.71421, 6.08579]},
			"faces": {
				"north": {"uv": [8, 4, 8.25, 4.5], "texture": "#1"},
				"east": {"uv": [4.5, 8, 4.75, 8.5], "texture": "#1"},
				"south": {"uv": [8, 4.5, 8.25, 5], "texture": "#1"},
				"west": {"uv": [5, 8, 5.25, 8.5], "texture": "#1"},
				"up": {"uv": [10.25, 7.75, 10, 7.5], "texture": "#1"},
				"down": {"uv": [8.25, 10, 8, 10.25], "texture": "#1"}
			}
		},
		{
			"from": [7.3, 4.91924, 7.71213],
			"to": [7.9, 5.21924, 8.01213],
			"rotation": {"angle": 0, "axis": "y", "origin": [5.9, 2.51924, 6.41213]},
			"faces": {
				"north": {"uv": [10, 6, 10.25, 6.25], "texture": "#1"},
				"east": {"uv": [6.5, 10, 6.75, 10.25], "texture": "#1"},
				"south": {"uv": [10, 6.5, 10.25, 6.75], "texture": "#1"},
				"west": {"uv": [7, 10, 7.25, 10.25], "texture": "#1"},
				"up": {"uv": [10.25, 7.25, 10, 7], "texture": "#1"},
				"down": {"uv": [7.75, 10, 7.5, 10.25], "texture": "#1"}
			}
		},
		{
			"from": [7.3, 4.4, 7.1],
			"to": [7.9, 4.7, 7.4],
			"rotation": {"angle": 0, "axis": "y", "origin": [5.9, 2, 5.5]},
			"faces": {
				"north": {"uv": [10, 4.5, 10.25, 4.75], "texture": "#1"},
				"east": {"uv": [5, 10, 5.25, 10.25], "texture": "#1"},
				"south": {"uv": [10, 5, 10.25, 5.25], "texture": "#1"},
				"west": {"uv": [5.5, 10, 5.75, 10.25], "texture": "#1"},
				"up": {"uv": [10.25, 5.75, 10, 5.5], "texture": "#1"},
				"down": {"uv": [6.25, 10, 6, 10.25], "texture": "#1"}
			}
		},
		{
			"from": [7.3, 2.91924, 7.71213],
			"to": [7.9, 3.21924, 8.01213],
			"rotation": {"angle": 0, "axis": "y", "origin": [5.9, 0.51924, 6.41213]},
			"faces": {
				"north": {"uv": [9.5, 8, 9.75, 8.25], "texture": "#1"},
				"east": {"uv": [8.5, 9.5, 8.75, 9.75], "texture": "#1"},
				"south": {"uv": [9.5, 8.5, 9.75, 8.75], "texture": "#1"},
				"west": {"uv": [9, 9.5, 9.25, 9.75], "texture": "#1"},
				"up": {"uv": [9.75, 9.25, 9.5, 9], "texture": "#1"},
				"down": {"uv": [9.75, 9.5, 9.5, 9.75], "texture": "#1"}
			}
		},
		{
			"from": [7.3, 3.71421, 7.58579],
			"to": [7.9, 4.51421, 7.88579],
			"rotation": {"angle": 45, "axis": "x", "origin": [5.9, 3.71421, 6.08579]},
			"faces": {
				"north": {"uv": [8, 1, 8.25, 1.5], "texture": "#1"},
				"east": {"uv": [8, 1.5, 8.25, 2], "texture": "#1"},
				"south": {"uv": [8, 2, 8.25, 2.5], "texture": "#1"},
				"west": {"uv": [8, 2.5, 8.25, 3], "texture": "#1"},
				"up": {"uv": [9.75, 7.75, 9.5, 7.5], "texture": "#1"},
				"down": {"uv": [8.25, 9.5, 8, 9.75], "texture": "#1"}
			}
		},
		{
			"from": [7.41, 0.01, 7.41],
			"to": [7.79, 0.49, 7.89],
			"rotation": {"angle": -45, "axis": "x", "origin": [5.8, 0, 5.9]},
			"faces": {
				"north": {"uv": [10.5, 4.5, 10.75, 4.75], "texture": "#1"},
				"east": {"uv": [5, 10.5, 5.25, 10.75], "texture": "#1"},
				"south": {"uv": [10.5, 5, 10.75, 5.25], "texture": "#1"},
				"west": {"uv": [5.5, 10.5, 5.75, 10.75], "texture": "#1"},
				"up": {"uv": [10.75, 5.75, 10.5, 5.5], "texture": "#1"},
				"down": {"uv": [6.25, 10.5, 6, 10.75], "texture": "#1"}
			}
		},
		{
			"from": [7.41, 9.01, 7.41],
			"to": [7.79, 9.49, 7.89],
			"rotation": {"angle": -45, "axis": "x", "origin": [5.8, 9, 5.9]},
			"faces": {
				"north": {"uv": [10.5, 6, 10.75, 6.25], "texture": "#1"},
				"east": {"uv": [6.5, 10.5, 6.75, 10.75], "texture": "#1"},
				"south": {"uv": [10.5, 6.5, 10.75, 6.75], "texture": "#1"},
				"west": {"uv": [7, 10.5, 7.25, 10.75], "texture": "#1"},
				"up": {"uv": [10.75, 7.25, 10.5, 7], "texture": "#1"},
				"down": {"uv": [7.75, 10.5, 7.5, 10.75], "texture": "#1"}
			}
		},
		{
			"from": [7.41, 16.01, 7.41],
			"to": [7.79, 16.49, 7.89],
			"rotation": {"angle": -45, "axis": "x", "origin": [5.8, 16, 5.9]},
			"faces": {
				"north": {"uv": [10.5, 7.5, 10.75, 7.75], "texture": "#1"},
				"east": {"uv": [8, 10.5, 8.25, 10.75], "texture": "#1"},
				"south": {"uv": [10.5, 8, 10.75, 8.25], "texture": "#1"},
				"west": {"uv": [8.5, 10.5, 8.75, 10.75], "texture": "#1"},
				"up": {"uv": [10.75, 8.75, 10.5, 8.5], "texture": "#1"},
				"down": {"uv": [9.25, 10.5, 9, 10.75], "texture": "#1"}
			}
		},
		{
			"from": [7.41, 22.81, 7.41],
			"to": [7.79, 23.29, 7.89],
			"rotation": {"angle": -45, "axis": "x", "origin": [5.8, 22.8, 5.9]},
			"faces": {
				"north": {"uv": [10.5, 9, 10.75, 9.25], "texture": "#1"},
				"east": {"uv": [9.5, 10.5, 9.75, 10.75], "texture": "#1"},
				"south": {"uv": [10.5, 9.5, 10.75, 9.75], "texture": "#1"},
				"west": {"uv": [10, 10.5, 10.25, 10.75], "texture": "#1"},
				"up": {"uv": [10.75, 10.25, 10.5, 10], "texture": "#1"},
				"down": {"uv": [10.75, 10.5, 10.5, 10.75], "texture": "#1"}
			}
		},
		{
			"from": [7, -0.9, 6.8],
			"to": [8.2, -0.4, 7.4],
			"rotation": {"angle": 0, "axis": "y", "origin": [8, -1.3, 6.3]},
			"faces": {
				"north": {"uv": [8.5, 2, 9, 2.25], "texture": "#1"},
				"east": {"uv": [11, 1, 11.25, 1.25], "texture": "#1"},
				"south": {"uv": [8.5, 2.5, 9, 2.75], "texture": "#1"},
				"west": {"uv": [11, 1.5, 11.25, 1.75], "texture": "#1"},
				"up": {"uv": [9, 3.25, 8.5, 3], "texture": "#1"},
				"down": {"uv": [4, 8.5, 3.5, 8.75], "texture": "#1"}
			}
		},
		{
			"from": [8.35724, -0.995, 7.83963],
			"to": [8.74724, -0.305, 8.52963],
			"rotation": {"angle": -22.5, "axis": "y", "origin": [6.75224, -2.3, 7.83463]},
			"faces": {
				"north": {"uv": [11, 2, 11.25, 2.25], "texture": "#1"},
				"east": {"uv": [11, 2.5, 11.25, 2.75], "texture": "#1"},
				"south": {"uv": [11, 3, 11.25, 3.25], "texture": "#1"},
				"west": {"uv": [3.5, 11, 3.75, 11.25], "texture": "#1"},
				"up": {"uv": [11.25, 3.75, 11, 3.5], "texture": "#1"},
				"down": {"uv": [4.25, 11, 4, 11.25], "texture": "#1"}
			}
		},
		{
			"from": [6.85712, -1, 8.84672],
			"to": [8.33212, -0.3, 9.24672],
			"rotation": {"angle": 0, "axis": "y", "origin": [8.33212, -2.3, 7.24672]},
			"faces": {
				"north": {"uv": [0.5, 7, 1.25, 7.25], "texture": "#1"},
				"east": {"uv": [11, 8.5, 11.25, 8.75], "texture": "#1"},
				"south": {"uv": [7, 1, 7.75, 1.25], "texture": "#1"},
				"west": {"uv": [9, 11, 9.25, 11.25], "texture": "#1"},
				"up": {"uv": [7.75, 1.75, 7, 1.5], "texture": "#1"},
				"down": {"uv": [7.75, 2, 7, 2.25], "texture": "#1"}
			}
		},
		{
			"from": [6.86788, -1, 5.05328],
			"to": [8.34288, -0.3, 5.45328],
			"rotation": {"angle": 0, "axis": "y", "origin": [8.36788, -2.3, 3.45328]},
			"faces": {
				"north": {"uv": [7, 2.5, 7.75, 2.75], "texture": "#1"},
				"east": {"uv": [11, 9, 11.25, 9.25], "texture": "#1"},
				"south": {"uv": [3.5, 7, 4.25, 7.25], "texture": "#1"},
				"west": {"uv": [9.5, 11, 9.75, 11.25], "texture": "#1"},
				"up": {"uv": [7.75, 3.75, 7, 3.5], "texture": "#1"},
				"down": {"uv": [7.75, 4, 7, 4.25], "texture": "#1"}
			}
		},
		{
			"from": [7.07121, -0.995, 4.46121],
			"to": [7.46121, -0.305, 5.15121],
			"rotation": {"angle": -22.5, "axis": "y", "origin": [5.46621, -2.3, 4.25621]},
			"faces": {
				"north": {"uv": [11, 7, 11.25, 7.25], "texture": "#1"},
				"east": {"uv": [7.5, 11, 7.75, 11.25], "texture": "#1"},
				"south": {"uv": [11, 7.5, 11.25, 7.75], "texture": "#1"},
				"west": {"uv": [8, 11, 8.25, 11.25], "texture": "#1"},
				"up": {"uv": [11.25, 8.25, 11, 8], "texture": "#1"},
				"down": {"uv": [8.75, 11, 8.5, 11.25], "texture": "#1"}
			}
		},
		{
			"from": [6.72679, -0.995, 9.21729],
			"to": [7.11679, -0.305, 9.90729],
			"rotation": {"angle": 22.5, "axis": "y", "origin": [5.12179, -2.3, 9.21229]},
			"faces": {
				"north": {"uv": [11, 4, 11.25, 4.25], "texture": "#1"},
				"east": {"uv": [4.5, 11, 4.75, 11.25], "texture": "#1"},
				"south": {"uv": [11, 4.5, 11.25, 4.75], "texture": "#1"},
				"west": {"uv": [5, 11, 5.25, 11.25], "texture": "#1"},
				"up": {"uv": [11.25, 5.25, 11, 5], "texture": "#1"},
				"down": {"uv": [5.75, 11, 5.5, 11.25], "texture": "#1"}
			}
		},
		{
			"from": [8.01283, -0.995, 5.83888],
			"to": [8.40283, -0.305, 6.52888],
			"rotation": {"angle": 22.5, "axis": "y", "origin": [6.40783, -2.3, 5.63388]},
			"faces": {
				"north": {"uv": [11, 5.5, 11.25, 5.75], "texture": "#1"},
				"east": {"uv": [6, 11, 6.25, 11.25], "texture": "#1"},
				"south": {"uv": [11, 6, 11.25, 6.25], "texture": "#1"},
				"west": {"uv": [6.5, 11, 6.75, 11.25], "texture": "#1"},
				"up": {"uv": [11.25, 6.75, 11, 6.5], "texture": "#1"},
				"down": {"uv": [7.25, 11, 7, 11.25], "texture": "#1"}
			}
		},
		{
			"from": [7.10783, -0.9, 6.13388],
			"to": [7.40783, -0.4, 7.33388],
			"rotation": {"angle": 22.5, "axis": "y", "origin": [5.40783, -2.3, 6.43388]},
			"faces": {
				"north": {"uv": [11, 9.5, 11.25, 9.75], "texture": "#1"},
				"east": {"uv": [8.5, 3.5, 9, 3.75], "texture": "#1"},
				"south": {"uv": [10, 11, 10.25, 11.25], "texture": "#1"},
				"west": {"uv": [4, 8.5, 4.5, 8.75], "texture": "#1"},
				"up": {"uv": [8.75, 4.5, 8.5, 4], "texture": "#1"},
				"down": {"uv": [4.75, 8.5, 4.5, 9], "texture": "#1"}
			}
		},
		{
			"from": [7.10783, -0.9, 6.86612],
			"to": [7.40783, -0.4, 8.06612],
			"rotation": {"angle": -22.5, "axis": "y", "origin": [5.40783, -2.3, 7.76612]},
			"faces": {
				"north": {"uv": [11, 10, 11.25, 10.25], "texture": "#1"},
				"east": {"uv": [8.5, 4.5, 9, 4.75], "texture": "#1"},
				"south": {"uv": [10.5, 11, 10.75, 11.25], "texture": "#1"},
				"west": {"uv": [5, 8.5, 5.5, 8.75], "texture": "#1"},
				"up": {"uv": [8.75, 5.5, 8.5, 5], "texture": "#1"},
				"down": {"uv": [5.75, 8.5, 5.5, 9], "texture": "#1"}
			}
		},
		{
			"from": [7.79217, -0.9, 6.86612],
			"to": [8.09217, -0.4, 8.06612],
			"rotation": {"angle": 22.5, "axis": "y", "origin": [9.79217, 1, 7.76612]},
			"faces": {
				"north": {"uv": [11.5, 0, 11.75, 0.25], "texture": "#1"},
				"east": {"uv": [8.5, 6.5, 9, 6.75], "texture": "#1"},
				"south": {"uv": [0.5, 11.5, 0.75, 11.75], "texture": "#1"},
				"west": {"uv": [7, 8.5, 7.5, 8.75], "texture": "#1"},
				"up": {"uv": [8.75, 7.5, 8.5, 7], "texture": "#1"},
				"down": {"uv": [7.75, 8.5, 7.5, 9], "texture": "#1"}
			}
		},
		{
			"from": [7.79217, -0.9, 6.13388],
			"to": [8.09217, -0.4, 7.33388],
			"rotation": {"angle": -22.5, "axis": "y", "origin": [9.79217, 1, 6.43388]},
			"faces": {
				"north": {"uv": [11, 10.5, 11.25, 10.75], "texture": "#1"},
				"east": {"uv": [8.5, 5.5, 9, 5.75], "texture": "#1"},
				"south": {"uv": [11, 11, 11.25, 11.25], "texture": "#1"},
				"west": {"uv": [6, 8.5, 6.5, 8.75], "texture": "#1"},
				"up": {"uv": [8.75, 6.5, 8.5, 6], "texture": "#1"},
				"down": {"uv": [6.75, 8.5, 6.5, 9], "texture": "#1"}
			}
		}
	],
	"gui_light": "front",
	"display": {
		"thirdperson_righthand": {
			"translation": [0.5, 10, 1.25]
		},
		"thirdperson_lefthand": {
			"translation": [-0.25, 10.5, 1.25]
		},
		"firstperson_righthand": {
			"translation": [3.25, 12.5, 0]
		},
		"firstperson_lefthand": {
			"translation": [3.25, 13.5, 0]
		},
		"ground": {
			"rotation": [45, 0, 0],
			"translation": [-0.5, 5.75, 0],
			"scale": [0.6, 0.6, 0.6]
		},
		"gui": {
			"rotation": [-90, -45, -90],
			"translation": [0.25, 0.75, 0],
			"scale": [0.7, 0.7, 0.7]
		},
		"fixed": {
			"rotation": [-90, 45, 90],
			"translation": [0.25, 0.75, -1.5]
		}
	}
}